oaieval/__init__.py
oaieval-1.0.6.dist-info/METADATA
oaieval-1.0.6.dist-info/WHEEL
oaieval-1.0.6.dist-info/entry_points.txt
oaieval-1.0.6.dist-info/top_level.txt
oaieval-1.0.6.dist-info/RECORD
