Metadata-Version: 2.1
Name: oaieval
Version: 1.0.6
Summary: Test package for OpenAI evaluation
Author: OpenAI
Author-email: adam@openai.com
Keywords: openai,evaluation,test
Requires-Dist: requests
